fileup/__init__.py
fileup/get.py
fileup/updater.py
fileup/urls.py
fileup.py-0.1.1.dist-info/LICENSE
fileup.py-0.1.1.dist-info/METADATA
fileup.py-0.1.1.dist-info/WHEEL
fileup.py-0.1.1.dist-info/entry_points.txt
fileup.py-0.1.1.dist-info/top_level.txt
fileup.py-0.1.1.dist-info/RECORD
